{ "backgroundcolor":"#ffffff",
 "compressionlevel":-1,
 "editorsettings":
    {
     "export":
        {
         "target":"."
        }
    },
 "height":15,
 "infinite":false,
 "layers":[
        {
         "compression":"zlib",
         "data":"eJzt0TERADAMxLCUP9gGQglk7f0QiYAHVwEAAAAAAAAASX129\/njhr+m+5MHqeUDww==",
         "encoding":"base64",
         "height":15,
         "id":1,
         "name":"Back Tiles",
         "opacity":1,
         "type":"tilelayer",
         "visible":true,
         "width":150,
         "x":0,
         "y":0
        }, 
        {
         "compression":"zlib",
         "data":"eJztmN0KwjAMhdfHmxd64xSmsI29P\/oIFqogJRlZaNYfzgeH3YSWpSfpz+y6boagxHpAkIEWL1A3k9P1FKu1H+GrJhiVPeUJX4ENSvPVZDg2OA7sg8CCEn2FflU\/pfkK+yCwAL6y4eKCJJx93NWFbytgHwwMPge3SHcmL3tiLdjj2Vzg3B6gzidcXqg7vaQ2NX6owUMU6FcB7twbe0sadzRUD9Xo13el43HxvddJOXdLcO+Kcc1t+eqdUdp3Uep\/Vye\/Xy7feGp+zd10bUz\/eZHWWR+txyujUvkqpT7PbjLS",
         "encoding":"base64",
         "height":15,
         "id":2,
         "name":"Middle Tiles",
         "opacity":1,
         "type":"tilelayer",
         "visible":true,
         "width":150,
         "x":0,
         "y":0
        }, 
        {
         "color":"#000000",
         "draworder":"topdown",
         "id":3,
         "name":"solid",
         "objects":[
                {
                 "height":64,
                 "id":1,
                 "name":"",
                 "rotation":0,
                 "type":"",
                 "visible":true,
                 "width":416,
                 "x":0,
                 "y":416
                }, 
                {
                 "height":64,
                 "id":2,
                 "name":"",
                 "rotation":0,
                 "type":"",
                 "visible":true,
                 "width":192,
                 "x":2432,
                 "y":320
                }, 
                {
                 "height":64,
                 "id":3,
                 "name":"",
                 "rotation":0,
                 "type":"",
                 "visible":true,
                 "width":192,
                 "x":2080,
                 "y":320
                }, 
                {
                 "height":32,
                 "id":4,
                 "name":"",
                 "rotation":0,
                 "type":"",
                 "visible":true,
                 "width":544,
                 "x":2080,
                 "y":448
                }, 
                {
                 "height":64,
                 "id":5,
                 "name":"",
                 "rotation":0,
                 "type":"",
                 "visible":true,
                 "width":608,
                 "x":3616,
                 "y":384
                }, 
                {
                 "height":320,
                 "id":6,
                 "name":"",
                 "rotation":0,
                 "type":"",
                 "visible":true,
                 "width":32,
                 "x":4768,
                 "y":64
                }, 
                {
                 "height":192,
                 "id":7,
                 "name":"",
                 "rotation":0,
                 "type":"",
                 "visible":true,
                 "width":480,
                 "x":3616,
                 "y":64
                }, 
                {
                 "height":352,
                 "id":8,
                 "name":"",
                 "rotation":0,
                 "type":"",
                 "visible":true,
                 "width":32,
                 "x":0,
                 "y":64
                }, 
                {
                 "height":64,
                 "id":9,
                 "name":"",
                 "rotation":0,
                 "type":"",
                 "visible":true,
                 "width":4800,
                 "x":0,
                 "y":0
                }, 
                {
                 "height":32,
                 "id":10,
                 "name":"",
                 "rotation":0,
                 "type":"",
                 "visible":true,
                 "width":64,
                 "x":2720,
                 "y":288
                }, 
                {
                 "height":32,
                 "id":11,
                 "name":"",
                 "rotation":0,
                 "type":"",
                 "visible":true,
                 "width":64,
                 "x":2880,
                 "y":352
                }, 
                {
                 "height":32,
                 "id":12,
                 "name":"",
                 "rotation":0,
                 "type":"",
                 "visible":true,
                 "width":96,
                 "x":3072,
                 "y":288
                }, 
                {
                 "height":32,
                 "id":13,
                 "name":"",
                 "rotation":0,
                 "type":"",
                 "visible":true,
                 "width":64,
                 "x":3296,
                 "y":352
                }, 
                {
                 "height":32,
                 "id":14,
                 "name":"",
                 "rotation":0,
                 "type":"",
                 "visible":true,
                 "width":64,
                 "x":3456,
                 "y":320
                }, 
                {
                 "height":32,
                 "id":15,
                 "name":"",
                 "rotation":0,
                 "type":"",
                 "visible":true,
                 "width":1184,
                 "x":3616,
                 "y":448
                }, 
                {
                 "height":64,
                 "id":16,
                 "name":"",
                 "rotation":0,
                 "type":"",
                 "visible":true,
                 "width":352,
                 "x":4256,
                 "y":384
                }, 
                {
                 "height":64,
                 "id":17,
                 "name":"",
                 "rotation":0,
                 "type":"",
                 "visible":true,
                 "width":160,
                 "x":4640,
                 "y":384
                }, 
                {
                 "height":64,
                 "id":18,
                 "name":"",
                 "rotation":0,
                 "type":"",
                 "visible":true,
                 "width":224,
                 "x":2400,
                 "y":384
                }, 
                {
                 "height":64,
                 "id":19,
                 "name":"",
                 "rotation":0,
                 "type":"",
                 "visible":true,
                 "width":224,
                 "x":2080,
                 "y":384
                }],
         "opacity":1,
         "type":"objectgroup",
         "visible":true,
         "x":0,
         "y":0
        }, 
        {
         "draworder":"topdown",
         "id":4,
         "name":"Collision Objects",
         "objects":[
                {
                 "height":0,
                 "id":20,
                 "name":"",
                 "polyline":[
                        {
                         "x":0,
                         "y":0
                        }, 
                        {
                         "x":256,
                         "y":0
                        }, 
                        {
                         "x":0,
                         "y":0
                        }],
                 "rotation":0,
                 "type":"moving_platform_path",
                 "visible":true,
                 "width":0,
                 "x":544,
                 "y":384
                }, 
                {
                 "height":0,
                 "id":21,
                 "name":"",
                 "polyline":[
                        {
                         "x":0,
                         "y":0
                        }, 
                        {
                         "x":-256,
                         "y":0
                        }, 
                        {
                         "x":0,
                         "y":0
                        }],
                 "rotation":0,
                 "type":"moving_platform_path",
                 "visible":true,
                 "width":0,
                 "x":1312,
                 "y":384
                }, 
                {
                 "height":0,
                 "id":22,
                 "name":"",
                 "polyline":[
                        {
                         "x":0,
                         "y":0
                        }, 
                        {
                         "x":256,
                         "y":0
                        }, 
                        {
                         "x":0,
                         "y":0
                        }],
                 "rotation":0,
                 "type":"moving_platform_path",
                 "visible":true,
                 "width":0,
                 "x":1568,
                 "y":384
                }, 
                {
                 "height":32,
                 "id":23,
                 "name":"",
                 "rotation":0,
                 "type":"spike_top",
                 "visible":true,
                 "width":1664,
                 "x":416,
                 "y":448
                }, 
                {
                 "height":32,
                 "id":24,
                 "name":"",
                 "rotation":0,
                 "type":"death",
                 "visible":true,
                 "width":992,
                 "x":2624,
                 "y":448
                }, 
                {
                 "height":320,
                 "id":25,
                 "name":"",
                 "properties":[
                        {
                         "name":"timeline",
                         "type":"string",
                         "value":"retux_boss2.json"
                        }],
                 "rotation":0,
                 "type":"timeline_switcher",
                 "visible":true,
                 "width":32,
                 "x":4416,
                 "y":64
                }, 
                {
                 "height":32,
                 "id":26,
                 "name":"",
                 "rotation":0,
                 "type":"spike_top",
                 "visible":true,
                 "width":32,
                 "x":4224,
                 "y":416
                }, 
                {
                 "height":32,
                 "id":27,
                 "name":"",
                 "rotation":0,
                 "type":"spike_top",
                 "visible":true,
                 "width":32,
                 "x":4608,
                 "y":416
                }, 
                {
                 "gid":502,
                 "height":96,
                 "id":28,
                 "name":"",
                 "properties":[
                        {
                         "name":"dest",
                         "type":"string",
                         "value":"retux-13.json:exit"
                        }, 
                        {
                         "name":"spawn_id",
                         "type":"string",
                         "value":"enter"
                        }],
                 "rotation":0,
                 "type":"",
                 "visible":true,
                 "width":32,
                 "x":96,
                 "y":416
                }],
         "opacity":1,
         "type":"objectgroup",
         "visible":true,
         "x":0,
         "y":0
        }, 
        {
         "color":"#00ff00",
         "draworder":"topdown",
         "id":5,
         "name":"warp",
         "objects":[],
         "opacity":1,
         "type":"objectgroup",
         "visible":true,
         "x":0,
         "y":0
        }, 
        {
         "color":"#005500",
         "draworder":"topdown",
         "id":6,
         "name":"warp_spawn",
         "objects":[],
         "opacity":1,
         "type":"objectgroup",
         "visible":true,
         "x":0,
         "y":0
        }, 
        {
         "draworder":"topdown",
         "id":7,
         "name":"Items",
         "objects":[
                {
                 "gid":479,
                 "height":32,
                 "id":29,
                 "name":"",
                 "rotation":0,
                 "type":"",
                 "visible":true,
                 "width":32,
                 "x":1472,
                 "y":288
                }, 
                {
                 "gid":479,
                 "height":32,
                 "id":30,
                 "name":"",
                 "rotation":0,
                 "type":"",
                 "visible":true,
                 "width":32,
                 "x":1504,
                 "y":288
                }, 
                {
                 "gid":479,
                 "height":32,
                 "id":31,
                 "name":"",
                 "rotation":0,
                 "type":"",
                 "visible":true,
                 "width":32,
                 "x":1440,
                 "y":320
                }, 
                {
                 "gid":479,
                 "height":32,
                 "id":32,
                 "name":"",
                 "rotation":0,
                 "type":"",
                 "visible":true,
                 "width":32,
                 "x":1536,
                 "y":320
                }, 
                {
                 "gid":479,
                 "height":32,
                 "id":33,
                 "name":"",
                 "rotation":0,
                 "type":"",
                 "visible":true,
                 "width":32,
                 "x":960,
                 "y":288
                }, 
                {
                 "gid":479,
                 "height":32,
                 "id":34,
                 "name":"",
                 "rotation":0,
                 "type":"",
                 "visible":true,
                 "width":32,
                 "x":992,
                 "y":288
                }, 
                {
                 "gid":479,
                 "height":32,
                 "id":35,
                 "name":"",
                 "rotation":0,
                 "type":"",
                 "visible":true,
                 "width":32,
                 "x":1024,
                 "y":320
                }, 
                {
                 "gid":479,
                 "height":32,
                 "id":36,
                 "name":"",
                 "rotation":0,
                 "type":"",
                 "visible":true,
                 "width":32,
                 "x":928,
                 "y":320
                }, 
                {
                 "gid":490,
                 "height":32,
                 "id":37,
                 "name":"",
                 "rotation":0,
                 "type":"",
                 "visible":true,
                 "width":32,
                 "x":2336,
                 "y":448
                }, 
                {
                 "gid":479,
                 "height":32,
                 "id":38,
                 "name":"",
                 "rotation":0,
                 "type":"",
                 "visible":true,
                 "width":32,
                 "x":2880,
                 "y":352
                }, 
                {
                 "gid":479,
                 "height":32,
                 "id":39,
                 "name":"",
                 "rotation":0,
                 "type":"",
                 "visible":true,
                 "width":32,
                 "x":2912,
                 "y":352
                }, 
                {
                 "gid":479,
                 "height":32,
                 "id":40,
                 "name":"",
                 "rotation":0,
                 "type":"",
                 "visible":true,
                 "width":32,
                 "x":2720,
                 "y":288
                }, 
                {
                 "gid":479,
                 "height":32,
                 "id":41,
                 "name":"",
                 "rotation":0,
                 "type":"",
                 "visible":true,
                 "width":32,
                 "x":2752,
                 "y":288
                }, 
                {
                 "gid":479,
                 "height":32,
                 "id":42,
                 "name":"",
                 "rotation":0,
                 "type":"",
                 "visible":true,
                 "width":32,
                 "x":3296,
                 "y":352
                }, 
                {
                 "gid":479,
                 "height":32,
                 "id":43,
                 "name":"",
                 "rotation":0,
                 "type":"",
                 "visible":true,
                 "width":32,
                 "x":3328,
                 "y":352
                }, 
                {
                 "gid":479,
                 "height":32,
                 "id":44,
                 "name":"",
                 "rotation":0,
                 "type":"",
                 "visible":true,
                 "width":32,
                 "x":3456,
                 "y":320
                }, 
                {
                 "gid":479,
                 "height":32,
                 "id":45,
                 "name":"",
                 "rotation":0,
                 "type":"",
                 "visible":true,
                 "width":32,
                 "x":3488,
                 "y":320
                }, 
                {
                 "gid":478,
                 "height":32,
                 "id":46,
                 "name":"",
                 "rotation":0,
                 "type":"",
                 "visible":true,
                 "width":32,
                 "x":256,
                 "y":320
                }, 
                {
                 "gid":470,
                 "height":32,
                 "id":47,
                 "name":"",
                 "rotation":0,
                 "type":"",
                 "visible":true,
                 "width":32,
                 "x":224,
                 "y":320
                }, 
                {
                 "gid":470,
                 "height":32,
                 "id":48,
                 "name":"",
                 "rotation":0,
                 "type":"",
                 "visible":true,
                 "width":32,
                 "x":288,
                 "y":320
                }, 
                {
                 "gid":488,
                 "height":32,
                 "id":49,
                 "name":"",
                 "properties":[
                        {
                         "name":"ID",
                         "type":"string",
                         "value":"bossblock1"
                        }],
                 "rotation":0,
                 "type":"",
                 "visible":true,
                 "width":32,
                 "x":4064,
                 "y":288
                }, 
                {
                 "gid":488,
                 "height":32,
                 "id":50,
                 "name":"",
                 "properties":[
                        {
                         "name":"ID",
                         "type":"string",
                         "value":"bossblock5"
                        }],
                 "rotation":0,
                 "type":"",
                 "visible":true,
                 "width":32,
                 "x":4064,
                 "y":320
                }, 
                {
                 "gid":488,
                 "height":32,
                 "id":51,
                 "name":"",
                 "properties":[
                        {
                         "name":"ID",
                         "type":"string",
                         "value":"bossblock9"
                        }],
                 "rotation":0,
                 "type":"",
                 "visible":true,
                 "width":32,
                 "x":4064,
                 "y":352
                }, 
                {
                 "gid":488,
                 "height":32,
                 "id":52,
                 "name":"",
                 "properties":[
                        {
                         "name":"ID",
                         "type":"string",
                         "value":"bossblock13"
                        }],
                 "rotation":0,
                 "type":"",
                 "visible":true,
                 "width":32,
                 "x":4064,
                 "y":384
                }],
         "opacity":1,
         "type":"objectgroup",
         "visible":true,
         "x":0,
         "y":0
        }, 
        {
         "draworder":"topdown",
         "id":8,
         "name":"Iceblocks",
         "objects":[
                {
                 "gid":489,
                 "height":32,
                 "id":53,
                 "name":"",
                 "rotation":0,
                 "type":"",
                 "visible":true,
                 "width":32,
                 "x":2336,
                 "y":448
                }, 
                {
                 "gid":489,
                 "height":32,
                 "id":54,
                 "name":"",
                 "rotation":0,
                 "type":"",
                 "visible":true,
                 "width":32,
                 "x":2304,
                 "y":352
                }, 
                {
                 "gid":489,
                 "height":32,
                 "id":55,
                 "name":"",
                 "rotation":0,
                 "type":"",
                 "visible":true,
                 "width":32,
                 "x":2368,
                 "y":352
                }, 
                {
                 "gid":489,
                 "height":32,
                 "id":56,
                 "name":"",
                 "rotation":0,
                 "type":"",
                 "visible":true,
                 "width":32,
                 "x":2336,
                 "y":352
                }, 
                {
                 "gid":489,
                 "height":32,
                 "id":57,
                 "name":"",
                 "rotation":0,
                 "type":"",
                 "visible":true,
                 "width":32,
                 "x":2304,
                 "y":384
                }, 
                {
                 "gid":489,
                 "height":32,
                 "id":58,
                 "name":"",
                 "rotation":0,
                 "type":"",
                 "visible":true,
                 "width":32,
                 "x":2336,
                 "y":384
                }, 
                {
                 "gid":489,
                 "height":32,
                 "id":59,
                 "name":"",
                 "rotation":0,
                 "type":"",
                 "visible":true,
                 "width":32,
                 "x":2368,
                 "y":384
                }, 
                {
                 "gid":489,
                 "height":32,
                 "id":60,
                 "name":"",
                 "rotation":0,
                 "type":"",
                 "visible":true,
                 "width":32,
                 "x":2304,
                 "y":416
                }, 
                {
                 "gid":489,
                 "height":32,
                 "id":61,
                 "name":"",
                 "rotation":0,
                 "type":"",
                 "visible":true,
                 "width":32,
                 "x":2336,
                 "y":416
                }, 
                {
                 "gid":489,
                 "height":32,
                 "id":62,
                 "name":"",
                 "rotation":0,
                 "type":"",
                 "visible":true,
                 "width":32,
                 "x":2368,
                 "y":416
                }, 
                {
                 "gid":489,
                 "height":32,
                 "id":63,
                 "name":"",
                 "rotation":0,
                 "type":"",
                 "visible":true,
                 "width":32,
                 "x":2272,
                 "y":384
                }, 
                {
                 "gid":489,
                 "height":32,
                 "id":64,
                 "name":"",
                 "rotation":0,
                 "type":"",
                 "visible":true,
                 "width":32,
                 "x":2400,
                 "y":384
                }, 
                {
                 "gid":489,
                 "height":32,
                 "id":65,
                 "name":"",
                 "rotation":0,
                 "type":"",
                 "visible":true,
                 "width":32,
                 "x":2272,
                 "y":352
                }, 
                {
                 "gid":489,
                 "height":32,
                 "id":66,
                 "name":"",
                 "rotation":0,
                 "type":"",
                 "visible":true,
                 "width":32,
                 "x":2400,
                 "y":352
                }, 
                {
                 "gid":489,
                 "height":32,
                 "id":67,
                 "name":"",
                 "rotation":0,
                 "type":"",
                 "visible":true,
                 "width":32,
                 "x":2368,
                 "y":448
                }, 
                {
                 "gid":489,
                 "height":32,
                 "id":68,
                 "name":"",
                 "rotation":0,
                 "type":"",
                 "visible":true,
                 "width":32,
                 "x":2304,
                 "y":448
                }],
         "opacity":1,
         "type":"objectgroup",
         "visible":true,
         "x":0,
         "y":0
        }, 
        {
         "draworder":"topdown",
         "id":9,
         "name":"NPCs",
         "objects":[
                {
                 "height":0,
                 "id":69,
                 "name":"",
                 "polyline":[
                        {
                         "x":0,
                         "y":0
                        }, 
                        {
                         "x":0,
                         "y":-96
                        }, 
                        {
                         "x":0,
                         "y":0
                        }],
                 "rotation":0,
                 "type":"flying_snowball_path",
                 "visible":true,
                 "width":0,
                 "x":480,
                 "y":416
                }, 
                {
                 "height":0,
                 "id":70,
                 "name":"",
                 "polyline":[
                        {
                         "x":0,
                         "y":0
                        }, 
                        {
                         "x":0,
                         "y":96
                        }, 
                        {
                         "x":0,
                         "y":0
                        }],
                 "rotation":0,
                 "type":"flying_snowball_path",
                 "visible":true,
                 "width":0,
                 "x":992,
                 "y":320
                }, 
                {
                 "height":0,
                 "id":71,
                 "name":"",
                 "polyline":[
                        {
                         "x":0,
                         "y":0
                        }, 
                        {
                         "x":0,
                         "y":-96
                        }, 
                        {
                         "x":0,
                         "y":0
                        }],
                 "rotation":0,
                 "type":"flying_snowball_path",
                 "visible":true,
                 "width":0,
                 "x":1504,
                 "y":416
                }, 
                {
                 "height":0,
                 "id":72,
                 "name":"",
                 "polyline":[
                        {
                         "x":0,
                         "y":0
                        }, 
                        {
                         "x":0,
                         "y":96
                        }, 
                        {
                         "x":0,
                         "y":0
                        }],
                 "rotation":0,
                 "type":"flying_snowball_path",
                 "visible":true,
                 "width":0,
                 "x":2016,
                 "y":320
                }, 
                {
                 "gid":9,
                 "height":32,
                 "id":73,
                 "name":"",
                 "rotation":0,
                 "type":"",
                 "visible":true,
                 "width":32,
                 "x":576,
                 "y":96
                }, 
                {
                 "gid":9,
                 "height":32,
                 "id":74,
                 "name":"",
                 "rotation":0,
                 "type":"",
                 "visible":true,
                 "width":32,
                 "x":864,
                 "y":96
                }, 
                {
                 "gid":9,
                 "height":32,
                 "id":75,
                 "name":"",
                 "rotation":0,
                 "type":"",
                 "visible":true,
                 "width":32,
                 "x":672,
                 "y":96
                }, 
                {
                 "gid":9,
                 "height":32,
                 "id":76,
                 "name":"",
                 "rotation":0,
                 "type":"",
                 "visible":true,
                 "width":32,
                 "x":768,
                 "y":96
                }, 
                {
                 "gid":9,
                 "height":32,
                 "id":77,
                 "name":"",
                 "rotation":0,
                 "type":"",
                 "visible":true,
                 "width":32,
                 "x":1088,
                 "y":96
                }, 
                {
                 "gid":9,
                 "height":32,
                 "id":78,
                 "name":"",
                 "rotation":0,
                 "type":"",
                 "visible":true,
                 "width":32,
                 "x":1184,
                 "y":96
                }, 
                {
                 "gid":9,
                 "height":32,
                 "id":79,
                 "name":"",
                 "rotation":0,
                 "type":"",
                 "visible":true,
                 "width":32,
                 "x":1280,
                 "y":96
                }, 
                {
                 "gid":9,
                 "height":32,
                 "id":80,
                 "name":"",
                 "rotation":0,
                 "type":"",
                 "visible":true,
                 "width":32,
                 "x":1376,
                 "y":96
                }, 
                {
                 "gid":9,
                 "height":32,
                 "id":81,
                 "name":"",
                 "rotation":0,
                 "type":"",
                 "visible":true,
                 "width":32,
                 "x":1600,
                 "y":96
                }, 
                {
                 "gid":9,
                 "height":32,
                 "id":82,
                 "name":"",
                 "rotation":0,
                 "type":"",
                 "visible":true,
                 "width":32,
                 "x":1696,
                 "y":96
                }, 
                {
                 "gid":9,
                 "height":32,
                 "id":83,
                 "name":"",
                 "rotation":0,
                 "type":"",
                 "visible":true,
                 "width":32,
                 "x":1792,
                 "y":96
                }, 
                {
                 "gid":9,
                 "height":32,
                 "id":84,
                 "name":"",
                 "rotation":0,
                 "type":"",
                 "visible":true,
                 "width":32,
                 "x":1888,
                 "y":96
                }, 
                {
                 "height":0,
                 "id":85,
                 "name":"",
                 "polyline":[
                        {
                         "x":0,
                         "y":0
                        }, 
                        {
                         "x":0,
                         "y":-96
                        }],
                 "rotation":0,
                 "type":"circoflame",
                 "visible":true,
                 "width":0,
                 "x":3104,
                 "y":288
                }, 
                {
                 "height":0,
                 "id":86,
                 "name":"",
                 "polyline":[
                        {
                         "x":0,
                         "y":0
                        }, 
                        {
                         "x":0,
                         "y":-64
                        }],
                 "rotation":0,
                 "type":"circoflame",
                 "visible":true,
                 "width":0,
                 "x":3104,
                 "y":288
                }, 
                {
                 "height":0,
                 "id":87,
                 "name":"",
                 "polyline":[
                        {
                         "x":0,
                         "y":0
                        }, 
                        {
                         "x":0,
                         "y":-32
                        }],
                 "rotation":0,
                 "type":"circoflame",
                 "visible":true,
                 "width":0,
                 "x":3104,
                 "y":288
                }, 
                {
                 "gid":9,
                 "height":32,
                 "id":88,
                 "name":"",
                 "rotation":0,
                 "type":"",
                 "visible":true,
                 "width":32,
                 "x":3040,
                 "y":96
                }, 
                {
                 "gid":9,
                 "height":32,
                 "id":89,
                 "name":"",
                 "rotation":0,
                 "type":"",
                 "visible":true,
                 "width":32,
                 "x":3168,
                 "y":96
                }, 
                {
                 "gid":9,
                 "height":32,
                 "id":90,
                 "name":"",
                 "rotation":0,
                 "type":"",
                 "visible":true,
                 "width":32,
                 "x":2880,
                 "y":96
                }, 
                {
                 "gid":9,
                 "height":32,
                 "id":91,
                 "name":"",
                 "rotation":0,
                 "type":"",
                 "visible":true,
                 "width":32,
                 "x":2912,
                 "y":96
                }, 
                {
                 "gid":9,
                 "height":32,
                 "id":92,
                 "name":"",
                 "rotation":0,
                 "type":"",
                 "visible":true,
                 "width":32,
                 "x":3296,
                 "y":96
                }, 
                {
                 "gid":9,
                 "height":32,
                 "id":93,
                 "name":"",
                 "rotation":0,
                 "type":"",
                 "visible":true,
                 "width":32,
                 "x":3328,
                 "y":96
                }, 
                {
                 "gid":9,
                 "height":32,
                 "id":94,
                 "name":"",
                 "rotation":0,
                 "type":"",
                 "visible":true,
                 "width":32,
                 "x":2720,
                 "y":96
                }, 
                {
                 "gid":9,
                 "height":32,
                 "id":95,
                 "name":"",
                 "rotation":0,
                 "type":"",
                 "visible":true,
                 "width":32,
                 "x":2752,
                 "y":96
                }, 
                {
                 "gid":9,
                 "height":32,
                 "id":96,
                 "name":"",
                 "rotation":0,
                 "type":"",
                 "visible":true,
                 "width":32,
                 "x":3456,
                 "y":96
                }, 
                {
                 "gid":9,
                 "height":32,
                 "id":97,
                 "name":"",
                 "rotation":0,
                 "type":"",
                 "visible":true,
                 "width":32,
                 "x":3488,
                 "y":96
                }, 
                {
                 "gid":501,
                 "height":64,
                 "id":98,
                 "name":"",
                 "rotation":0,
                 "type":"",
                 "visible":true,
                 "width":57,
                 "x":4672,
                 "y":416
                }, 
                {
                 "gid":9,
                 "height":32,
                 "id":99,
                 "name":"",
                 "rotation":0,
                 "type":"",
                 "visible":true,
                 "width":32,
                 "x":3104,
                 "y":96
                }, 
                {
                 "gid":12,
                 "height":32,
                 "id":100,
                 "name":"",
                 "rotation":0,
                 "type":"",
                 "visible":true,
                 "width":32,
                 "x":4320,
                 "y":96
                }, 
                {
                 "gid":12,
                 "height":32,
                 "id":101,
                 "name":"",
                 "rotation":0,
                 "type":"",
                 "visible":true,
                 "width":32,
                 "x":4512,
                 "y":96
                }, 
                {
                 "gid":12,
                 "height":32,
                 "id":102,
                 "name":"",
                 "rotation":0,
                 "type":"",
                 "visible":true,
                 "width":32,
                 "x":4672,
                 "y":96
                }, 
                {
                 "gid":12,
                 "height":32,
                 "id":103,
                 "name":"",
                 "rotation":0,
                 "type":"",
                 "visible":true,
                 "width":32,
                 "x":4160,
                 "y":96
                }],
         "opacity":1,
         "type":"objectgroup",
         "visible":true,
         "x":0,
         "y":0
        }, 
        {
         "draworder":"topdown",
         "id":10,
         "name":"Players",
         "objects":[
                {
                 "gid":1,
                 "height":32,
                 "id":104,
                 "name":"",
                 "rotation":0,
                 "type":"",
                 "visible":true,
                 "width":32,
                 "x":160,
                 "y":416
                }],
         "opacity":1,
         "type":"objectgroup",
         "visible":true,
         "x":0,
         "y":0
        }, 
        {
         "compression":"zlib",
         "data":"eJztwQENAAAAwqD3T20PBxQAAAAAAAAAAPwbIygAAQ==",
         "encoding":"base64",
         "height":15,
         "id":11,
         "name":"Front Tiles",
         "opacity":1,
         "type":"tilelayer",
         "visible":true,
         "width":150,
         "x":0,
         "y":0
        }],
 "nextlayerid":12,
 "nextobjectid":105,
 "orientation":"orthogonal",
 "properties":[
        {
         "name":"bgname",
         "type":"string",
         "value":"arctis_castle"
        }, 
        {
         "name":"music",
         "type":"string",
         "value":"fortress.ogg"
        }],
 "renderorder":"right-down",
 "tiledversion":"1.3.4",
 "tileheight":32,
 "tilesets":[
        {
         "firstgid":1,
         "source":"..\/tilesets\/creatures.json"
        }, 
        {
         "firstgid":16,
         "source":"..\/tilesets\/snow.json"
        }, 
        {
         "firstgid":254,
         "source":"..\/tilesets\/cave.json"
        }, 
        {
         "firstgid":326,
         "source":"..\/tilesets\/castle.json"
        }, 
        {
         "firstgid":356,
         "source":"..\/tilesets\/blocks.json"
        }, 
        {
         "firstgid":380,
         "source":"..\/tilesets\/pipes.json"
        }, 
        {
         "firstgid":468,
         "source":"..\/tilesets\/special_blocks.json"
        }, 
        {
         "firstgid":493,
         "source":"..\/tilesets\/decoration_small.json"
        }, 
        {
         "firstgid":497,
         "source":"..\/tilesets\/igloo.json"
        }, 
        {
         "firstgid":499,
         "source":"..\/tilesets\/krush.json"
        }, 
        {
         "firstgid":500,
         "source":"..\/tilesets\/krosh.json"
        }, 
        {
         "firstgid":501,
         "source":"..\/tilesets\/snowman.json"
        }, 
        {
         "firstgid":502,
         "source":"..\/tilesets\/door.json"
        }],
 "tilewidth":32,
 "type":"map",
 "version":1.2,
 "width":150
}