{ "compressionlevel":-1,
 "height":28,
 "infinite":false,
 "layers":[
        {
         "compression":"zlib",
         "data":"eJzt07ENABAARFEGs3\/JSEagEVzeS66\/5pcCAAAAAAAAAAAAAAAAAADAr0a9\/QA4resc4ukc8ukc8ukc8ukc8ukc8ukc8q06b5sDAAAA3jAB1SsJtA==",
         "encoding":"base64",
         "height":28,
         "id":1,
         "name":"Back Tiles",
         "opacity":1,
         "type":"tilelayer",
         "visible":true,
         "width":250,
         "x":0,
         "y":0
        }, 
        {
         "compression":"zlib",
         "data":"eJztnMuKFTEQhnPeQLyMO3V04UYd8bZQR\/GCV4TRhaLCjIJXEAUFfTvdODvdOC9kBQ0cQzpdSaqr0vJ\/8OGmoZPu+qvT4+k4BwAAAAAAYjYXzm0trEcBAJiSV5Tx18j5bHlC7rUeBDBjF7nOcGPxR86xJVrWHnfuc5+nz\/gb8rDhGACPmprk1NYBcrehe5jjnALNuVvNM2T8M3nS4PygjJqa5PTvx+TdJZ+RhxRddXYZOJYZl7QW81zOuB8Dct4\/NTVZc1\/fO7usa6+XwzU9Tp5gjnWt03mmXM64FznvH62ce1JZ52ahNgc+A1Osl3NrmnBNL5AXK8fdyzxTLmfci5z3j2bOPXHWNbMgYeg3uWuguW7XNtVvkfP+Ka3J5+TDxnNKrOHvuH\/f\/7nG561dJ\/SS85b1vpTIef+U1KTP+Aeh87ZmXfLdIedQP8n1uviajmVxk9waOM8U3mbMO\/U+VXMtQB+EmhyrRcmMB3zmSusvKPnuEEzVds15uL0z5PtdxTla4Iwv9T6F5\/Z8Gbrnce+WzjhnLLne01pzqaxL1fZYjqzyHah9r0DO58vQPbe4p9yeI7VW5Kzha65D\/NuBWKt8B0rfK4LI+XwZqkmLdy6LnjOW9f+xtsf60JB4DwcSWK0t4r8ToLYBmI6e1hYAAAAAABr0ukfHVfJaxut2QwNgdvS6R8cGeT\/jA7uhAWKf9QBAEb3m\/Ay5n7xCniaPkqf+\/rtCnrMbGiCOWA+gM76S35ze956lpvbi6WUPJ5\/1swmR8WG09iG6zDzu6QRzvEH1ejPjLcXn1iPyBfmD\/Ols98WR+F5Wcx8rKeN+1TqHHWb9rPMOmwStfYjuMY9762TvYS+EfL8kP5KfXPr\/80v2j\/BKf1NW+ntg6z28JPqV5hysett511Znsa1196XxOkrtGyj1nPpObrvxfAd7+Wae+92N9HeyrfU35lpiHrVzqKl1q952MBpHL3UWq\/07aake\/4vcceP5ljKXk5K65H53k8tITQ5y9Se1drnk8s86SafuW7GWewZonlsq5yU9XmN+3HNM2ac1nucarrr8sy625f7G9+M3wmRgzA==",
         "encoding":"base64",
         "height":28,
         "id":2,
         "name":"Middle Tiles",
         "opacity":1,
         "type":"tilelayer",
         "visible":true,
         "width":250,
         "x":0,
         "y":0
        }, 
        {
         "color":"#000000",
         "draworder":"topdown",
         "id":3,
         "name":"solid",
         "objects":[
                {
                 "height":64,
                 "id":1,
                 "name":"",
                 "rotation":0,
                 "type":"",
                 "visible":true,
                 "width":960,
                 "x":0,
                 "y":832
                }, 
                {
                 "height":64,
                 "id":2,
                 "name":"",
                 "rotation":0,
                 "type":"",
                 "visible":true,
                 "width":32,
                 "x":1792,
                 "y":704
                }, 
                {
                 "height":160,
                 "id":3,
                 "name":"",
                 "rotation":0,
                 "type":"",
                 "visible":true,
                 "width":224,
                 "x":1696,
                 "y":320
                }, 
                {
                 "height":96,
                 "id":4,
                 "name":"",
                 "rotation":0,
                 "type":"",
                 "visible":true,
                 "width":96,
                 "x":1920,
                 "y":320
                }, 
                {
                 "height":128,
                 "id":5,
                 "name":"",
                 "rotation":0,
                 "type":"",
                 "visible":true,
                 "width":1152,
                 "x":960,
                 "y":768
                }, 
                {
                 "height":96,
                 "id":6,
                 "name":"",
                 "rotation":0,
                 "type":"",
                 "visible":true,
                 "width":544,
                 "x":2112,
                 "y":800
                }, 
                {
                 "height":128,
                 "id":7,
                 "name":"",
                 "rotation":0,
                 "type":"",
                 "visible":true,
                 "width":448,
                 "x":1696,
                 "y":192
                }, 
                {
                 "height":32,
                 "id":8,
                 "name":"",
                 "rotation":0,
                 "type":"",
                 "visible":true,
                 "width":288,
                 "x":2784,
                 "y":736
                }, 
                {
                 "height":128,
                 "id":9,
                 "name":"",
                 "rotation":0,
                 "type":"",
                 "visible":true,
                 "width":1472,
                 "x":5568,
                 "y":768
                }, 
                {
                 "height":64,
                 "id":10,
                 "name":"",
                 "rotation":0,
                 "type":"",
                 "visible":true,
                 "width":800,
                 "x":3200,
                 "y":832
                }, 
                {
                 "height":160,
                 "id":11,
                 "name":"",
                 "rotation":0,
                 "type":"",
                 "visible":true,
                 "width":1440,
                 "x":4000,
                 "y":736
                }, 
                {
                 "height":32,
                 "id":12,
                 "name":"",
                 "rotation":0,
                 "type":"",
                 "visible":true,
                 "width":96,
                 "x":7040,
                 "y":864
                }, 
                {
                 "height":128,
                 "id":13,
                 "name":"",
                 "rotation":0,
                 "type":"",
                 "visible":true,
                 "width":864,
                 "x":7136,
                 "y":768
                }, 
                {
                 "height":32,
                 "id":14,
                 "name":"",
                 "rotation":0,
                 "type":"",
                 "visible":true,
                 "width":1056,
                 "x":2400,
                 "y":160
                }, 
                {
                 "height":32,
                 "id":15,
                 "name":"",
                 "rotation":0,
                 "type":"",
                 "visible":true,
                 "width":768,
                 "x":2720,
                 "y":192
                }, 
                {
                 "height":32,
                 "id":16,
                 "name":"",
                 "rotation":0,
                 "type":"",
                 "visible":true,
                 "width":800,
                 "x":2720,
                 "y":224
                }, 
                {
                 "height":128,
                 "id":17,
                 "name":"",
                 "rotation":0,
                 "type":"",
                 "visible":true,
                 "width":96,
                 "x":2720,
                 "y":256
                }, 
                {
                 "height":288,
                 "id":18,
                 "name":"",
                 "rotation":0,
                 "type":"",
                 "visible":true,
                 "width":224,
                 "x":2816,
                 "y":256
                }, 
                {
                 "height":192,
                 "id":19,
                 "name":"",
                 "rotation":0,
                 "type":"",
                 "visible":true,
                 "width":160,
                 "x":3040,
                 "y":256
                }, 
                {
                 "height":64,
                 "id":20,
                 "name":"",
                 "rotation":0,
                 "type":"",
                 "visible":true,
                 "width":608,
                 "x":3200,
                 "y":256
                }, 
                {
                 "height":96,
                 "id":21,
                 "name":"",
                 "rotation":0,
                 "type":"",
                 "visible":true,
                 "width":416,
                 "x":3808,
                 "y":256
                }, 
                {
                 "height":160,
                 "id":22,
                 "name":"",
                 "rotation":0,
                 "type":"",
                 "visible":true,
                 "width":224,
                 "x":3808,
                 "y":352
                }, 
                {
                 "height":288,
                 "id":23,
                 "name":"",
                 "rotation":0,
                 "type":"",
                 "visible":true,
                 "width":256,
                 "x":4416,
                 "y":160
                }, 
                {
                 "height":32,
                 "id":24,
                 "name":"",
                 "rotation":0,
                 "type":"",
                 "visible":true,
                 "width":640,
                 "x":4672,
                 "y":160
                }, 
                {
                 "height":32,
                 "id":25,
                 "name":"",
                 "rotation":0,
                 "type":"",
                 "visible":true,
                 "width":672,
                 "x":4672,
                 "y":192
                }, 
                {
                 "height":32,
                 "id":26,
                 "name":"",
                 "rotation":0,
                 "type":"",
                 "visible":true,
                 "width":704,
                 "x":4672,
                 "y":224
                }, 
                {
                 "height":96,
                 "id":27,
                 "name":"",
                 "rotation":0,
                 "type":"",
                 "visible":true,
                 "width":1696,
                 "x":4672,
                 "y":256
                }, 
                {
                 "height":128,
                 "id":28,
                 "name":"",
                 "rotation":0,
                 "type":"",
                 "visible":true,
                 "width":32,
                 "x":6336,
                 "y":128
                }, 
                {
                 "height":128,
                 "id":29,
                 "name":"",
                 "rotation":0,
                 "type":"",
                 "visible":true,
                 "width":480,
                 "x":5696,
                 "y":352
                }, 
                {
                 "height":32,
                 "id":30,
                 "name":"",
                 "rotation":0,
                 "type":"",
                 "visible":true,
                 "width":64,
                 "x":5248,
                 "y":704
                }, 
                {
                 "height":32,
                 "id":31,
                 "name":"",
                 "rotation":0,
                 "type":"",
                 "visible":true,
                 "width":64,
                 "x":2720,
                 "y":128
                }, 
                {
                 "height":128,
                 "id":32,
                 "name":"",
                 "rotation":0,
                 "type":"",
                 "visible":true,
                 "width":64,
                 "x":7936,
                 "y":640
                }],
         "opacity":1,
         "type":"objectgroup",
         "visible":true,
         "x":0,
         "y":0
        }, 
        {
         "draworder":"topdown",
         "id":4,
         "name":"Collision Objects",
         "objects":[
                {
                 "height":32,
                 "id":33,
                 "name":"",
                 "rotation":0,
                 "type":"slope_topright",
                 "visible":true,
                 "width":32,
                 "x":2112,
                 "y":768
                }, 
                {
                 "height":96,
                 "id":34,
                 "name":"",
                 "rotation":0,
                 "type":"slope_bottomright",
                 "visible":true,
                 "width":96,
                 "x":2016,
                 "y":320
                }, 
                {
                 "height":768,
                 "id":35,
                 "name":"",
                 "rotation":0,
                 "type":"level_end",
                 "visible":true,
                 "width":32,
                 "x":7424,
                 "y":0
                }, 
                {
                 "height":96,
                 "id":36,
                 "name":"",
                 "rotation":0,
                 "type":"slope_topleft",
                 "visible":true,
                 "width":192,
                 "x":3808,
                 "y":736
                }, 
                {
                 "height":192,
                 "id":37,
                 "name":"",
                 "rotation":0,
                 "type":"slope_bottomleft",
                 "visible":true,
                 "width":192,
                 "x":2528,
                 "y":192
                }, 
                {
                 "height":192,
                 "id":38,
                 "name":"",
                 "rotation":0,
                 "type":"slope_bottomleft",
                 "visible":true,
                 "width":192,
                 "x":3616,
                 "y":320
                }, 
                {
                 "height":96,
                 "id":39,
                 "name":"",
                 "rotation":0,
                 "type":"slope_bottomright",
                 "visible":true,
                 "width":192,
                 "x":4672,
                 "y":352
                }, 
                {
                 "height":128,
                 "id":40,
                 "name":"",
                 "rotation":0,
                 "type":"slope_topleft",
                 "visible":true,
                 "width":128,
                 "x":6208,
                 "y":128
                }, 
                {
                 "height":32,
                 "id":41,
                 "name":"",
                 "rotation":0,
                 "type":"solid_top",
                 "visible":true,
                 "width":64,
                 "x":5248,
                 "y":608
                }, 
                {
                 "height":32,
                 "id":42,
                 "name":"",
                 "rotation":0,
                 "type":"solid_top",
                 "visible":true,
                 "width":64,
                 "x":2720,
                 "y":64
                }, 
                {
                 "height":32,
                 "id":43,
                 "name":"",
                 "rotation":0,
                 "type":"solid_top",
                 "visible":true,
                 "width":288,
                 "x":6464,
                 "y":640
                }],
         "opacity":1,
         "type":"objectgroup",
         "visible":true,
         "x":0,
         "y":0
        }, 
        {
         "color":"#00ff00",
         "draworder":"topdown",
         "id":5,
         "name":"warp",
         "objects":[],
         "opacity":1,
         "type":"objectgroup",
         "visible":true,
         "x":0,
         "y":0
        }, 
        {
         "color":"#005500",
         "draworder":"topdown",
         "id":6,
         "name":"warp_spawn",
         "objects":[],
         "opacity":1,
         "type":"objectgroup",
         "visible":true,
         "x":0,
         "y":0
        }, 
        {
         "draworder":"topdown",
         "id":7,
         "name":"Items",
         "objects":[
                {
                 "gid":440,
                 "height":32,
                 "id":44,
                 "name":"",
                 "rotation":0,
                 "type":"",
                 "visible":true,
                 "width":32,
                 "x":288,
                 "y":736
                }, 
                {
                 "gid":440,
                 "height":32,
                 "id":45,
                 "name":"",
                 "rotation":0,
                 "type":"",
                 "visible":true,
                 "width":32,
                 "x":320,
                 "y":736
                }, 
                {
                 "gid":440,
                 "height":32,
                 "id":46,
                 "name":"",
                 "rotation":0,
                 "type":"",
                 "visible":true,
                 "width":32,
                 "x":416,
                 "y":736
                }, 
                {
                 "gid":440,
                 "height":32,
                 "id":47,
                 "name":"",
                 "rotation":0,
                 "type":"",
                 "visible":true,
                 "width":32,
                 "x":448,
                 "y":736
                }, 
                {
                 "gid":440,
                 "height":32,
                 "id":48,
                 "name":"",
                 "rotation":0,
                 "type":"",
                 "visible":true,
                 "width":32,
                 "x":544,
                 "y":736
                }, 
                {
                 "gid":440,
                 "height":32,
                 "id":49,
                 "name":"",
                 "rotation":0,
                 "type":"",
                 "visible":true,
                 "width":32,
                 "x":576,
                 "y":736
                }, 
                {
                 "gid":440,
                 "height":32,
                 "id":50,
                 "name":"",
                 "rotation":0,
                 "type":"",
                 "visible":true,
                 "width":32,
                 "x":2368,
                 "y":704
                }, 
                {
                 "gid":440,
                 "height":32,
                 "id":51,
                 "name":"",
                 "rotation":0,
                 "type":"",
                 "visible":true,
                 "width":32,
                 "x":2400,
                 "y":704
                }, 
                {
                 "gid":440,
                 "height":32,
                 "id":52,
                 "name":"",
                 "rotation":0,
                 "type":"",
                 "visible":true,
                 "width":32,
                 "x":2496,
                 "y":704
                }, 
                {
                 "gid":440,
                 "height":32,
                 "id":53,
                 "name":"",
                 "rotation":0,
                 "type":"",
                 "visible":true,
                 "width":32,
                 "x":2528,
                 "y":704
                }, 
                {
                 "gid":440,
                 "height":32,
                 "id":54,
                 "name":"",
                 "rotation":0,
                 "type":"",
                 "visible":true,
                 "width":32,
                 "x":2272,
                 "y":704
                }, 
                {
                 "gid":440,
                 "height":32,
                 "id":55,
                 "name":"",
                 "rotation":0,
                 "type":"",
                 "visible":true,
                 "width":32,
                 "x":2240,
                 "y":704
                }, 
                {
                 "gid":438,
                 "height":32,
                 "id":56,
                 "name":"",
                 "rotation":0,
                 "type":"",
                 "visible":true,
                 "width":32,
                 "x":2272,
                 "y":576
                }, 
                {
                 "gid":438,
                 "height":32,
                 "id":57,
                 "name":"",
                 "rotation":0,
                 "type":"",
                 "visible":true,
                 "width":32,
                 "x":2304,
                 "y":576
                }, 
                {
                 "gid":438,
                 "height":32,
                 "id":58,
                 "name":"",
                 "rotation":0,
                 "type":"",
                 "visible":true,
                 "width":32,
                 "x":2336,
                 "y":576
                }, 
                {
                 "gid":438,
                 "height":32,
                 "id":59,
                 "name":"",
                 "rotation":0,
                 "type":"",
                 "visible":true,
                 "width":32,
                 "x":2368,
                 "y":576
                }, 
                {
                 "gid":438,
                 "height":32,
                 "id":60,
                 "name":"",
                 "rotation":0,
                 "type":"",
                 "visible":true,
                 "width":32,
                 "x":2400,
                 "y":576
                }, 
                {
                 "gid":438,
                 "height":32,
                 "id":61,
                 "name":"",
                 "rotation":0,
                 "type":"",
                 "visible":true,
                 "width":32,
                 "x":2432,
                 "y":576
                }, 
                {
                 "gid":438,
                 "height":32,
                 "id":62,
                 "name":"",
                 "rotation":0,
                 "type":"",
                 "visible":true,
                 "width":32,
                 "x":2464,
                 "y":576
                }, 
                {
                 "gid":438,
                 "height":32,
                 "id":63,
                 "name":"",
                 "rotation":0,
                 "type":"",
                 "visible":true,
                 "width":32,
                 "x":2496,
                 "y":576
                }, 
                {
                 "gid":447,
                 "height":32,
                 "id":64,
                 "name":"",
                 "rotation":0,
                 "type":"",
                 "visible":true,
                 "width":32,
                 "x":2464,
                 "y":704
                }, 
                {
                 "gid":447,
                 "height":32,
                 "id":65,
                 "name":"",
                 "rotation":0,
                 "type":"",
                 "visible":true,
                 "width":32,
                 "x":2432,
                 "y":704
                }, 
                {
                 "gid":447,
                 "height":32,
                 "id":66,
                 "name":"",
                 "rotation":0,
                 "type":"",
                 "visible":true,
                 "width":32,
                 "x":2336,
                 "y":704
                }, 
                {
                 "gid":447,
                 "height":32,
                 "id":67,
                 "name":"",
                 "rotation":0,
                 "type":"",
                 "visible":true,
                 "width":32,
                 "x":2304,
                 "y":704
                }, 
                {
                 "gid":459,
                 "height":32,
                 "id":68,
                 "name":"",
                 "rotation":0,
                 "type":"",
                 "visible":true,
                 "width":32,
                 "x":7040,
                 "y":800
                }, 
                {
                 "gid":459,
                 "height":32,
                 "id":69,
                 "name":"",
                 "rotation":0,
                 "type":"",
                 "visible":true,
                 "width":32,
                 "x":7072,
                 "y":800
                }, 
                {
                 "gid":459,
                 "height":32,
                 "id":70,
                 "name":"",
                 "rotation":0,
                 "type":"",
                 "visible":true,
                 "width":32,
                 "x":7104,
                 "y":800
                }, 
                {
                 "gid":460,
                 "height":32,
                 "id":71,
                 "name":"",
                 "rotation":0,
                 "type":"",
                 "visible":true,
                 "width":32,
                 "x":7072,
                 "y":864
                }, 
                {
                 "gid":448,
                 "height":32,
                 "id":72,
                 "name":"",
                 "rotation":0,
                 "type":"",
                 "visible":true,
                 "width":32,
                 "x":6496,
                 "y":512
                }, 
                {
                 "gid":448,
                 "height":32,
                 "id":73,
                 "name":"",
                 "rotation":0,
                 "type":"",
                 "visible":true,
                 "width":32,
                 "x":6688,
                 "y":512
                }, 
                {
                 "gid":449,
                 "height":32,
                 "id":74,
                 "name":"",
                 "rotation":0,
                 "type":"",
                 "visible":true,
                 "width":32,
                 "x":6528,
                 "y":576
                }, 
                {
                 "gid":449,
                 "height":32,
                 "id":75,
                 "name":"",
                 "rotation":0,
                 "type":"",
                 "visible":true,
                 "width":32,
                 "x":6560,
                 "y":544
                }, 
                {
                 "gid":449,
                 "height":32,
                 "id":76,
                 "name":"",
                 "rotation":0,
                 "type":"",
                 "visible":true,
                 "width":32,
                 "x":6592,
                 "y":576
                }, 
                {
                 "gid":449,
                 "height":32,
                 "id":77,
                 "name":"",
                 "rotation":0,
                 "type":"",
                 "visible":true,
                 "width":32,
                 "x":6624,
                 "y":544
                }, 
                {
                 "gid":449,
                 "height":32,
                 "id":78,
                 "name":"",
                 "rotation":0,
                 "type":"",
                 "visible":true,
                 "width":32,
                 "x":6656,
                 "y":576
                }, 
                {
                 "gid":442,
                 "height":32,
                 "id":79,
                 "name":"",
                 "rotation":0,
                 "type":"",
                 "visible":true,
                 "width":32,
                 "x":6464,
                 "y":384
                }, 
                {
                 "gid":442,
                 "height":32,
                 "id":80,
                 "name":"",
                 "rotation":0,
                 "type":"",
                 "visible":true,
                 "width":32,
                 "x":6432,
                 "y":256
                }, 
                {
                 "gid":440,
                 "height":32,
                 "id":81,
                 "name":"",
                 "rotation":0,
                 "type":"",
                 "visible":true,
                 "width":32,
                 "x":4544,
                 "y":640
                }, 
                {
                 "gid":440,
                 "height":32,
                 "id":82,
                 "name":"",
                 "rotation":0,
                 "type":"",
                 "visible":true,
                 "width":32,
                 "x":4416,
                 "y":640
                }, 
                {
                 "gid":440,
                 "height":32,
                 "id":83,
                 "name":"",
                 "rotation":0,
                 "type":"",
                 "visible":true,
                 "width":32,
                 "x":4672,
                 "y":640
                }, 
                {
                 "gid":448,
                 "height":32,
                 "id":84,
                 "name":"",
                 "rotation":0,
                 "type":"",
                 "visible":true,
                 "width":32,
                 "x":4608,
                 "y":640
                }, 
                {
                 "gid":448,
                 "height":32,
                 "id":85,
                 "name":"",
                 "rotation":0,
                 "type":"",
                 "visible":true,
                 "width":32,
                 "x":4480,
                 "y":640
                }, 
                {
                 "gid":440,
                 "height":32,
                 "id":86,
                 "name":"",
                 "rotation":0,
                 "type":"",
                 "visible":true,
                 "width":32,
                 "x":3360,
                 "y":736
                }, 
                {
                 "gid":440,
                 "height":32,
                 "id":87,
                 "name":"",
                 "rotation":0,
                 "type":"",
                 "visible":true,
                 "width":32,
                 "x":3392,
                 "y":736
                }, 
                {
                 "gid":440,
                 "height":32,
                 "id":88,
                 "name":"",
                 "rotation":0,
                 "type":"",
                 "visible":true,
                 "width":32,
                 "x":3424,
                 "y":736
                }, 
                {
                 "gid":440,
                 "height":32,
                 "id":89,
                 "name":"",
                 "rotation":0,
                 "type":"",
                 "visible":true,
                 "width":32,
                 "x":3456,
                 "y":736
                }, 
                {
                 "gid":440,
                 "height":32,
                 "id":90,
                 "name":"",
                 "rotation":0,
                 "type":"",
                 "visible":true,
                 "width":32,
                 "x":3488,
                 "y":736
                }, 
                {
                 "gid":440,
                 "height":32,
                 "id":91,
                 "name":"",
                 "rotation":0,
                 "type":"",
                 "visible":true,
                 "width":32,
                 "x":3520,
                 "y":736
                }, 
                {
                 "gid":439,
                 "height":32,
                 "id":92,
                 "name":"",
                 "rotation":0,
                 "type":"",
                 "visible":true,
                 "width":32,
                 "x":1728,
                 "y":192
                }, 
                {
                 "gid":448,
                 "height":32,
                 "id":93,
                 "name":"",
                 "rotation":0,
                 "type":"",
                 "visible":true,
                 "width":32,
                 "x":2080,
                 "y":192
                }, 
                {
                 "gid":452,
                 "height":32,
                 "id":94,
                 "name":"",
                 "properties":[
                        {
                         "name":"text",
                         "type":"string",
                         "value":"Traveler's Note:\\n\\nI swear, there are no fire flowers anywhere in this level! How am I supposed to melt this ice?! What's more, that ledge over there is shaped like a grin, almost like it's taunting me!"
                        }],
                 "rotation":0,
                 "type":"",
                 "visible":true,
                 "width":32,
                 "x":6944,
                 "y":672
                }],
         "opacity":1,
         "type":"objectgroup",
         "visible":true,
         "x":0,
         "y":0
        }, 
        {
         "draworder":"topdown",
         "id":8,
         "name":"NPCs",
         "objects":[
                {
                 "gid":3,
                 "height":32,
                 "id":95,
                 "name":"",
                 "rotation":0,
                 "type":"",
                 "visible":true,
                 "width":32,
                 "x":1280,
                 "y":768
                }, 
                {
                 "gid":3,
                 "height":32,
                 "id":96,
                 "name":"",
                 "rotation":0,
                 "type":"",
                 "visible":true,
                 "width":32,
                 "x":1344,
                 "y":768
                }, 
                {
                 "gid":9,
                 "height":32,
                 "id":97,
                 "name":"",
                 "rotation":0,
                 "type":"",
                 "visible":true,
                 "width":32,
                 "x":1728,
                 "y":512
                }, 
                {
                 "gid":9,
                 "height":32,
                 "id":98,
                 "name":"",
                 "rotation":0,
                 "type":"",
                 "visible":true,
                 "width":32,
                 "x":1760,
                 "y":512
                }, 
                {
                 "gid":9,
                 "height":32,
                 "id":99,
                 "name":"",
                 "rotation":0,
                 "type":"",
                 "visible":true,
                 "width":32,
                 "x":1792,
                 "y":512
                }, 
                {
                 "gid":9,
                 "height":32,
                 "id":100,
                 "name":"",
                 "rotation":0,
                 "type":"",
                 "visible":true,
                 "width":32,
                 "x":1824,
                 "y":512
                }, 
                {
                 "gid":9,
                 "height":32,
                 "id":101,
                 "name":"",
                 "rotation":0,
                 "type":"",
                 "visible":true,
                 "width":32,
                 "x":1856,
                 "y":512
                }, 
                {
                 "gid":3,
                 "height":32,
                 "id":102,
                 "name":"",
                 "rotation":0,
                 "type":"",
                 "visible":true,
                 "width":32,
                 "x":2528,
                 "y":672
                }, 
                {
                 "gid":3,
                 "height":32,
                 "id":103,
                 "name":"",
                 "rotation":0,
                 "type":"",
                 "visible":true,
                 "width":32,
                 "x":2464,
                 "y":672
                }, 
                {
                 "gid":2,
                 "height":32,
                 "id":104,
                 "name":"",
                 "rotation":0,
                 "type":"",
                 "visible":true,
                 "width":32,
                 "x":2624,
                 "y":800
                }, 
                {
                 "gid":2,
                 "height":32,
                 "id":105,
                 "name":"",
                 "rotation":0,
                 "type":"",
                 "visible":true,
                 "width":32,
                 "x":2560,
                 "y":800
                }, 
                {
                 "gid":2,
                 "height":32,
                 "id":106,
                 "name":"",
                 "rotation":0,
                 "type":"",
                 "visible":true,
                 "width":32,
                 "x":2496,
                 "y":800
                }, 
                {
                 "gid":2,
                 "height":32,
                 "id":107,
                 "name":"",
                 "rotation":0,
                 "type":"",
                 "visible":true,
                 "width":32,
                 "x":2304,
                 "y":800
                }, 
                {
                 "gid":2,
                 "height":32,
                 "id":108,
                 "name":"",
                 "rotation":0,
                 "type":"",
                 "visible":true,
                 "width":32,
                 "x":2240,
                 "y":800
                }, 
                {
                 "gid":9,
                 "height":32,
                 "id":109,
                 "name":"",
                 "rotation":0,
                 "type":"",
                 "visible":true,
                 "width":32,
                 "x":2912,
                 "y":576
                }, 
                {
                 "gid":9,
                 "height":32,
                 "id":110,
                 "name":"",
                 "rotation":0,
                 "type":"",
                 "visible":true,
                 "width":32,
                 "x":2848,
                 "y":576
                }, 
                {
                 "gid":9,
                 "height":32,
                 "id":111,
                 "name":"",
                 "rotation":0,
                 "type":"",
                 "visible":true,
                 "width":32,
                 "x":2976,
                 "y":576
                }, 
                {
                 "gid":3,
                 "height":32,
                 "id":112,
                 "name":"",
                 "rotation":0,
                 "type":"",
                 "visible":true,
                 "width":32,
                 "x":3040,
                 "y":736
                }, 
                {
                 "gid":3,
                 "height":32,
                 "id":113,
                 "name":"",
                 "rotation":0,
                 "type":"",
                 "visible":true,
                 "width":32,
                 "x":2976,
                 "y":736
                }, 
                {
                 "gid":3,
                 "height":32,
                 "id":114,
                 "name":"",
                 "rotation":0,
                 "type":"",
                 "visible":true,
                 "width":32,
                 "x":6688,
                 "y":640
                }, 
                {
                 "gid":3,
                 "height":32,
                 "id":115,
                 "name":"",
                 "rotation":0,
                 "type":"",
                 "visible":true,
                 "width":32,
                 "x":6560,
                 "y":640
                }, 
                {
                 "gid":2,
                 "height":32,
                 "id":116,
                 "name":"",
                 "rotation":0,
                 "type":"",
                 "visible":true,
                 "width":32,
                 "x":6272,
                 "y":768
                }, 
                {
                 "gid":2,
                 "height":32,
                 "id":117,
                 "name":"",
                 "rotation":0,
                 "type":"",
                 "visible":true,
                 "width":32,
                 "x":6208,
                 "y":768
                }, 
                {
                 "gid":2,
                 "height":32,
                 "id":118,
                 "name":"",
                 "rotation":0,
                 "type":"",
                 "visible":true,
                 "width":32,
                 "x":6144,
                 "y":768
                }, 
                {
                 "gid":2,
                 "height":32,
                 "id":119,
                 "name":"",
                 "rotation":0,
                 "type":"",
                 "visible":true,
                 "width":32,
                 "x":6016,
                 "y":768
                }, 
                {
                 "gid":2,
                 "height":32,
                 "id":120,
                 "name":"",
                 "rotation":0,
                 "type":"",
                 "visible":true,
                 "width":32,
                 "x":5952,
                 "y":768
                }, 
                {
                 "gid":2,
                 "height":32,
                 "id":121,
                 "name":"",
                 "rotation":0,
                 "type":"",
                 "visible":true,
                 "width":32,
                 "x":5888,
                 "y":768
                }, 
                {
                 "gid":9,
                 "height":32,
                 "id":122,
                 "name":"",
                 "rotation":0,
                 "type":"",
                 "visible":true,
                 "width":32,
                 "x":5920,
                 "y":512
                }, 
                {
                 "gid":9,
                 "height":32,
                 "id":123,
                 "name":"",
                 "rotation":0,
                 "type":"",
                 "visible":true,
                 "width":32,
                 "x":5856,
                 "y":512
                }, 
                {
                 "gid":9,
                 "height":32,
                 "id":124,
                 "name":"",
                 "rotation":0,
                 "type":"",
                 "visible":true,
                 "width":32,
                 "x":5792,
                 "y":512
                }, 
                {
                 "gid":9,
                 "height":32,
                 "id":125,
                 "name":"",
                 "rotation":0,
                 "type":"",
                 "visible":true,
                 "width":32,
                 "x":5728,
                 "y":512
                }, 
                {
                 "gid":9,
                 "height":32,
                 "id":126,
                 "name":"",
                 "rotation":0,
                 "type":"",
                 "visible":true,
                 "width":32,
                 "x":5984,
                 "y":512
                }, 
                {
                 "gid":9,
                 "height":32,
                 "id":127,
                 "name":"",
                 "rotation":0,
                 "type":"",
                 "visible":true,
                 "width":32,
                 "x":6048,
                 "y":512
                }, 
                {
                 "gid":9,
                 "height":32,
                 "id":128,
                 "name":"",
                 "rotation":0,
                 "type":"",
                 "visible":true,
                 "width":32,
                 "x":6112,
                 "y":512
                }, 
                {
                 "gid":9,
                 "height":32,
                 "id":129,
                 "name":"",
                 "rotation":0,
                 "type":"",
                 "visible":true,
                 "width":32,
                 "x":6496,
                 "y":544
                }, 
                {
                 "gid":9,
                 "height":32,
                 "id":130,
                 "name":"",
                 "rotation":0,
                 "type":"",
                 "visible":true,
                 "width":32,
                 "x":6688,
                 "y":544
                }, 
                {
                 "gid":9,
                 "height":32,
                 "id":131,
                 "name":"",
                 "rotation":0,
                 "type":"",
                 "visible":true,
                 "width":32,
                 "x":3840,
                 "y":544
                }, 
                {
                 "gid":9,
                 "height":32,
                 "id":132,
                 "name":"",
                 "rotation":0,
                 "type":"",
                 "visible":true,
                 "width":32,
                 "x":3904,
                 "y":544
                }, 
                {
                 "gid":9,
                 "height":32,
                 "id":133,
                 "name":"",
                 "rotation":0,
                 "type":"",
                 "visible":true,
                 "width":32,
                 "x":3968,
                 "y":544
                }, 
                {
                 "gid":9,
                 "height":32,
                 "id":134,
                 "name":"",
                 "rotation":0,
                 "type":"",
                 "visible":true,
                 "width":32,
                 "x":4512,
                 "y":480
                }, 
                {
                 "gid":9,
                 "height":32,
                 "id":135,
                 "name":"",
                 "rotation":0,
                 "type":"",
                 "visible":true,
                 "width":32,
                 "x":4576,
                 "y":480
                }, 
                {
                 "gid":9,
                 "height":32,
                 "id":136,
                 "name":"",
                 "rotation":0,
                 "type":"",
                 "visible":true,
                 "width":32,
                 "x":4448,
                 "y":480
                }, 
                {
                 "gid":9,
                 "height":32,
                 "id":137,
                 "name":"",
                 "rotation":0,
                 "type":"",
                 "visible":true,
                 "width":32,
                 "x":4640,
                 "y":480
                }, 
                {
                 "gid":2,
                 "height":32,
                 "id":138,
                 "name":"",
                 "rotation":0,
                 "type":"",
                 "visible":true,
                 "width":32,
                 "x":5440,
                 "y":256
                }, 
                {
                 "gid":2,
                 "height":32,
                 "id":139,
                 "name":"",
                 "rotation":0,
                 "type":"",
                 "visible":true,
                 "width":32,
                 "x":5504,
                 "y":256
                }, 
                {
                 "gid":2,
                 "height":32,
                 "id":140,
                 "name":"",
                 "rotation":0,
                 "type":"",
                 "visible":true,
                 "width":32,
                 "x":5568,
                 "y":256
                }, 
                {
                 "gid":3,
                 "height":32,
                 "id":141,
                 "name":"",
                 "rotation":0,
                 "type":"",
                 "visible":true,
                 "width":32,
                 "x":5696,
                 "y":256
                }, 
                {
                 "gid":3,
                 "height":32,
                 "id":142,
                 "name":"",
                 "rotation":0,
                 "type":"",
                 "visible":true,
                 "width":32,
                 "x":5760,
                 "y":256
                }, 
                {
                 "gid":4,
                 "height":32,
                 "id":143,
                 "name":"",
                 "rotation":0,
                 "type":"",
                 "visible":true,
                 "width":32,
                 "x":4032,
                 "y":736
                }, 
                {
                 "gid":4,
                 "height":32,
                 "id":144,
                 "name":"",
                 "rotation":0,
                 "type":"",
                 "visible":true,
                 "width":32,
                 "x":4128,
                 "y":736
                }, 
                {
                 "gid":2,
                 "height":32,
                 "id":145,
                 "name":"",
                 "rotation":0,
                 "type":"",
                 "visible":true,
                 "width":32,
                 "x":3904,
                 "y":768
                }, 
                {
                 "gid":2,
                 "height":32,
                 "id":146,
                 "name":"",
                 "rotation":0,
                 "type":"",
                 "visible":true,
                 "width":32,
                 "x":3840,
                 "y":800
                }, 
                {
                 "gid":2,
                 "height":32,
                 "id":147,
                 "name":"",
                 "rotation":0,
                 "type":"",
                 "visible":true,
                 "width":32,
                 "x":3776,
                 "y":832
                }, 
                {
                 "gid":3,
                 "height":32,
                 "id":148,
                 "name":"",
                 "rotation":0,
                 "type":"",
                 "visible":true,
                 "width":32,
                 "x":4320,
                 "y":736
                }, 
                {
                 "gid":3,
                 "height":32,
                 "id":149,
                 "name":"",
                 "rotation":0,
                 "type":"",
                 "visible":true,
                 "width":32,
                 "x":4384,
                 "y":736
                }, 
                {
                 "gid":2,
                 "height":32,
                 "id":150,
                 "name":"",
                 "rotation":0,
                 "type":"",
                 "visible":true,
                 "width":32,
                 "x":5184,
                 "y":736
                }, 
                {
                 "gid":2,
                 "height":32,
                 "id":151,
                 "name":"",
                 "rotation":0,
                 "type":"",
                 "visible":true,
                 "width":32,
                 "x":5120,
                 "y":736
                }, 
                {
                 "gid":2,
                 "height":32,
                 "id":152,
                 "name":"",
                 "rotation":0,
                 "type":"",
                 "visible":true,
                 "width":32,
                 "x":4992,
                 "y":736
                }, 
                {
                 "gid":2,
                 "height":32,
                 "id":153,
                 "name":"",
                 "rotation":0,
                 "type":"",
                 "visible":true,
                 "width":32,
                 "x":4928,
                 "y":736
                }, 
                {
                 "gid":3,
                 "height":32,
                 "id":154,
                 "name":"",
                 "rotation":0,
                 "type":"",
                 "visible":true,
                 "width":32,
                 "x":3488,
                 "y":704
                }, 
                {
                 "gid":3,
                 "height":32,
                 "id":155,
                 "name":"",
                 "rotation":0,
                 "type":"",
                 "visible":true,
                 "width":32,
                 "x":4512,
                 "y":160
                }, 
                {
                 "gid":2,
                 "height":32,
                 "id":156,
                 "name":"",
                 "rotation":0,
                 "type":"",
                 "visible":true,
                 "width":32,
                 "x":4640,
                 "y":160
                }, 
                {
                 "gid":2,
                 "height":32,
                 "id":157,
                 "name":"",
                 "rotation":0,
                 "type":"",
                 "visible":true,
                 "width":32,
                 "x":4704,
                 "y":160
                }, 
                {
                 "gid":2,
                 "height":32,
                 "id":158,
                 "name":"",
                 "rotation":0,
                 "type":"",
                 "visible":true,
                 "width":32,
                 "x":4768,
                 "y":160
                }, 
                {
                 "gid":3,
                 "height":32,
                 "id":159,
                 "name":"",
                 "rotation":0,
                 "type":"",
                 "visible":true,
                 "width":32,
                 "x":4128,
                 "y":256
                }, 
                {
                 "gid":3,
                 "height":32,
                 "id":160,
                 "name":"",
                 "rotation":0,
                 "type":"",
                 "visible":true,
                 "width":32,
                 "x":4064,
                 "y":256
                }, 
                {
                 "gid":3,
                 "height":32,
                 "id":161,
                 "name":"",
                 "rotation":0,
                 "type":"",
                 "visible":true,
                 "width":32,
                 "x":4000,
                 "y":256
                }, 
                {
                 "gid":3,
                 "height":32,
                 "id":162,
                 "name":"",
                 "rotation":0,
                 "type":"",
                 "visible":true,
                 "width":32,
                 "x":3712,
                 "y":256
                }, 
                {
                 "gid":3,
                 "height":32,
                 "id":163,
                 "name":"",
                 "rotation":0,
                 "type":"",
                 "visible":true,
                 "width":32,
                 "x":3648,
                 "y":256
                }, 
                {
                 "gid":4,
                 "height":32,
                 "id":164,
                 "name":"",
                 "rotation":0,
                 "type":"",
                 "visible":true,
                 "width":32,
                 "x":3232,
                 "y":160
                }, 
                {
                 "gid":4,
                 "height":32,
                 "id":165,
                 "name":"",
                 "rotation":0,
                 "type":"",
                 "visible":true,
                 "width":32,
                 "x":3168,
                 "y":160
                }, 
                {
                 "gid":2,
                 "height":32,
                 "id":166,
                 "name":"",
                 "rotation":0,
                 "type":"",
                 "visible":true,
                 "width":32,
                 "x":3008,
                 "y":160
                }, 
                {
                 "gid":2,
                 "height":32,
                 "id":167,
                 "name":"",
                 "rotation":0,
                 "type":"",
                 "visible":true,
                 "width":32,
                 "x":2944,
                 "y":160
                }, 
                {
                 "gid":2,
                 "height":32,
                 "id":168,
                 "name":"",
                 "rotation":0,
                 "type":"",
                 "visible":true,
                 "width":32,
                 "x":2880,
                 "y":160
                }, 
                {
                 "gid":2,
                 "height":32,
                 "id":169,
                 "name":"",
                 "rotation":0,
                 "type":"",
                 "visible":true,
                 "width":32,
                 "x":2816,
                 "y":160
                }, 
                {
                 "gid":2,
                 "height":32,
                 "id":170,
                 "name":"",
                 "rotation":0,
                 "type":"",
                 "visible":true,
                 "width":32,
                 "x":1504,
                 "y":768
                }, 
                {
                 "gid":2,
                 "height":32,
                 "id":171,
                 "name":"",
                 "rotation":0,
                 "type":"",
                 "visible":true,
                 "width":32,
                 "x":1568,
                 "y":768
                }, 
                {
                 "gid":2,
                 "height":32,
                 "id":172,
                 "name":"",
                 "rotation":0,
                 "type":"",
                 "visible":true,
                 "width":32,
                 "x":1632,
                 "y":768
                }, 
                {
                 "gid":2,
                 "height":32,
                 "id":173,
                 "name":"",
                 "rotation":0,
                 "type":"",
                 "visible":true,
                 "width":32,
                 "x":5120,
                 "y":160
                }, 
                {
                 "gid":2,
                 "height":32,
                 "id":174,
                 "name":"",
                 "rotation":0,
                 "type":"",
                 "visible":true,
                 "width":32,
                 "x":5056,
                 "y":160
                }, 
                {
                 "gid":2,
                 "height":32,
                 "id":175,
                 "name":"",
                 "rotation":0,
                 "type":"",
                 "visible":true,
                 "width":32,
                 "x":3392,
                 "y":160
                }, 
                {
                 "gid":2,
                 "height":32,
                 "id":176,
                 "name":"",
                 "rotation":0,
                 "type":"",
                 "visible":true,
                 "width":32,
                 "x":3328,
                 "y":160
                }],
         "opacity":1,
         "type":"objectgroup",
         "visible":true,
         "x":0,
         "y":0
        }, 
        {
         "draworder":"topdown",
         "id":9,
         "name":"Players",
         "objects":[
                {
                 "gid":1,
                 "height":32,
                 "id":177,
                 "name":"",
                 "rotation":0,
                 "type":"",
                 "visible":true,
                 "width":32,
                 "x":96,
                 "y":832
                }],
         "opacity":1,
         "type":"objectgroup",
         "visible":true,
         "x":0,
         "y":0
        }, 
        {
         "compression":"zlib",
         "data":"eJzt1DERACAQA8HHvzgoEIQFGgbI7CpIc6kCAAAAAAAAAAAAAAAAAADgd6PdXgCc1nUO8XQO+XQO+XQO+XQO+XQO+XQO+XY6n74AAAAAnrcAOsYIJw==",
         "encoding":"base64",
         "height":28,
         "id":10,
         "name":"Front Tiles",
         "opacity":1,
         "type":"tilelayer",
         "visible":true,
         "width":250,
         "x":0,
         "y":0
        }],
 "nextlayerid":11,
 "nextobjectid":178,
 "orientation":"orthogonal",
 "properties":[
        {
         "name":"background_y",
         "type":"int",
         "value":448
        }, 
        {
         "name":"bgname",
         "type":"string",
         "value":"arctis"
        }, 
        {
         "name":"music",
         "type":"string",
         "value":"chipdisko.ogg"
        }, 
        {
         "name":"name",
         "type":"string",
         "value":"May The Fourth Be With You"
        }],
 "renderorder":"right-down",
 "tiledversion":"1.3.4",
 "tileheight":32,
 "tilesets":[
        {
         "firstgid":1,
         "source":"..\/tilesets\/creatures.tsx"
        }, 
        {
         "firstgid":16,
         "source":"..\/tilesets\/snow.tsx"
        }, 
        {
         "firstgid":254,
         "source":"..\/tilesets\/cave.tsx"
        }, 
        {
         "firstgid":326,
         "source":"..\/tilesets\/blocks.tsx"
        }, 
        {
         "firstgid":350,
         "source":"..\/tilesets\/pipes.tsx"
        }, 
        {
         "firstgid":438,
         "source":"..\/tilesets\/special_blocks.tsx"
        }, 
        {
         "firstgid":463,
         "source":"..\/tilesets\/decoration_small.tsx"
        }, 
        {
         "firstgid":467,
         "source":"..\/tilesets\/igloo.tsx"
        }, 
        {
         "firstgid":469,
         "source":"..\/tilesets\/krush.tsx"
        }, 
        {
         "firstgid":470,
         "source":"..\/tilesets\/krosh.tsx"
        }, 
        {
         "firstgid":471,
         "source":"..\/tilesets\/snowman.tsx"
        }],
 "tilewidth":32,
 "type":"map",
 "version":1.2,
 "width":250
}